phlex/__init__.py
phlex/cli.py
phlex/phlexparsers.py
phlex/phlexstructure.py
phlex-1.0.0.dist-info/DESCRIPTION.rst
phlex-1.0.0.dist-info/METADATA
phlex-1.0.0.dist-info/RECORD
phlex-1.0.0.dist-info/WHEEL
phlex-1.0.0.dist-info/entry_points.txt
phlex-1.0.0.dist-info/metadata.json
phlex-1.0.0.dist-info/top_level.txt
