Metadata-Version: 2.0
Name: phlex
Version: 1.0.0
Summary: Flexible static HTML builder
Home-page: https://github.com/lxndrdagreat/phlex
Author: Dan Alexander
Author-email: lxndrdagreat@gmail.com
License: MIT
Platform: any
Classifier: Development Status :: 5 - Production/Stable
Classifier: Environment :: Console
Classifier: Intended Audience :: Developers
Classifier: License :: OSI Approved :: MIT License
Classifier: Operating System :: POSIX
Classifier: Operating System :: MacOS
Classifier: Operating System :: Unix
Classifier: Operating System :: Microsoft :: Windows
Classifier: Programming Language :: Python :: 3
Classifier: Topic :: Software Development :: Libraries :: Python Modules
Requires-Dist: Jinja2
Requires-Dist: click
Requires-Dist: markdown
Requires-Dist: pyyaml
